<annotation><folder>VOC2007</folder><filename>img_07520.jpg</filename><source><database>Kggle</database></source><owner><name>Leo</name></owner><size><width>1280</width><height>720</height><depth>3</depth></size><segmented>0</segmented><object><name>alb</name><pose>Unspecified</pose><truncated>0</truncated><difficult>0</difficult><bndbox><xmin>597.927863957</xmin><ymin>337.702920348</ymin><xmax>985.317747648</xmax><ymax>477.500139245</ymax></bndbox></object><object><name>alb</name><pose>Unspecified</pose><truncated>0</truncated><difficult>0</difficult><bndbox><xmin>256.856335925</xmin><ymin>105.268990133</ymin><xmax>562.557483272</xmax><ymax>205.48506874</ymax></bndbox></object></annotation>