<annotation><folder>VOC2007</folder><filename>img_01367.jpg</filename><source><database>Kggle</database></source><owner><name>Leo</name></owner><size><width>1276</width><height>718</height><depth>3</depth></size><segmented>0</segmented><object><name>alb</name><pose>Unspecified</pose><truncated>0</truncated><difficult>0</difficult><bndbox><xmin>517.721314995</xmin><ymin>318.232367933</ymin><xmax>604.40401223</xmax><ymax>491.597762403</ymax></bndbox></object><object><name>alb</name><pose>Unspecified</pose><truncated>0</truncated><difficult>0</difficult><bndbox><xmin>908.387169658</xmin><ymin>167.428223427</ymin><xmax>1111.43841935</xmax><ymax>239.861710158</ymax></bndbox></object></annotation>