<?xml version="1.0" ?>
<annotation>
  <folder>training_data</folder>
  <filename>Buffy_56.jpg</filename>
  <source>
    <database>The oxford hand Database</database>
    <annotation/>
  </source>
  <size>
    <width>503</width>
    <height>586</height>
    <depth>3</depth>
  </size>
  <segmented>0</segmented>
  <object>
    <name>hand photo</name>
    <difficult>0</difficult>
    <bnd_box>
      <xmin>161.511703513</xmin>
      <xmax>190.488296487</xmax>
      <ymin>375.437987646</ymin>
      <ymax>424.562012354</ymax>
    </bnd_box>
  </object>
  <object>
    <name>hand photo</name>
    <difficult>0</difficult>
    <bnd_box>
      <xmin>194.96439666</xmin>
      <xmax>253.03560334</xmax>
      <ymin>402.845718858</ymin>
      <ymax>441.154281142</ymax>
    </bnd_box>
  </object>
</annotation>
