<?xml version="1.0" ?>
<annotation>
  <folder>training_data</folder>
  <filename>Inria_350.jpg</filename>
  <source>
    <database>The oxford hand Database</database>
    <annotation/>
  </source>
  <size>
    <width>681</width>
    <height>976</height>
    <depth>3</depth>
  </size>
  <segmented>0</segmented>
  <object>
    <name>hand photo</name>
    <difficult>0</difficult>
    <bnd_box>
      <xmin>49.5839127395</xmin>
      <xmax>80.1714636046</xmax>
      <ymin>282.574838104</ymin>
      <ymax>334.006861242</ymax>
    </bnd_box>
  </object>
  <object>
    <name>hand photo</name>
    <difficult>0</difficult>
    <bnd_box>
      <xmin>161.335883944</xmin>
      <xmax>193.588847238</xmax>
      <ymin>419.340016376</ymin>
      <ymax>452.405081663</ymax>
    </bnd_box>
  </object>
</annotation>
