<?xml version="1.0" ?>
<annotation>
  <folder>validation_data</folder>
  <filename>Movie_4weds_36.jpg</filename>
  <source>
    <database>The oxford hand Database</database>
    <annotation/>
  </source>
  <size>
    <width>720</width>
    <height>576</height>
    <depth>3</depth>
  </size>
  <segmented>0</segmented>
  <object>
    <name>hand photo</name>
    <difficult>0</difficult>
    <bnd_box>
      <xmin>138.923451174</xmin>
      <xmax>182.721710117</xmax>
      <ymin>327.549040708</ymin>
      <ymax>367.26914111</ymax>
    </bnd_box>
  </object>
</annotation>
