<?xml version="1.0" ?>
<annotation>
  <folder>validation_data</folder>
  <filename>Movie_forrest_159.jpg</filename>
  <source>
    <database>The oxford hand Database</database>
    <annotation/>
  </source>
  <size>
    <width>720</width>
    <height>390</height>
    <depth>3</depth>
  </size>
  <segmented>0</segmented>
  <object>
    <name>hand photo</name>
    <difficult>0</difficult>
    <bnd_box>
      <xmin>196.315830019</xmin>
      <xmax>253.071266755</xmax>
      <ymin>126.96581224</ymin>
      <ymax>200.089382566</ymax>
    </bnd_box>
  </object>
</annotation>
