<?xml version="1.0" ?>
<annotation>
  <folder>training_data</folder>
  <filename>VOC2010_740.jpg</filename>
  <source>
    <database>The oxford hand Database</database>
    <annotation/>
  </source>
  <size>
    <width>500</width>
    <height>375</height>
    <depth>3</depth>
  </size>
  <segmented>0</segmented>
  <object>
    <name>hand photo</name>
    <difficult>0</difficult>
    <bnd_box>
      <xmin>131.638043581</xmin>
      <xmax>235.721403424</xmax>
      <ymin>172.732585077</ymin>
      <ymax>250.24402311</ymax>
    </bnd_box>
  </object>
  <object>
    <name>hand photo</name>
    <difficult>0</difficult>
    <bnd_box>
      <xmin>216.800998766</xmin>
      <xmax>323.369508147</xmax>
      <ymin>183.390057947</ymin>
      <ymax>281.203509305</ymax>
    </bnd_box>
  </object>
</annotation>
