<?xml version="1.0" ?>
<annotation>
  <folder>training_data</folder>
  <filename>VOC2010_560.jpg</filename>
  <source>
    <database>The oxford hand Database</database>
    <annotation/>
  </source>
  <size>
    <width>500</width>
    <height>375</height>
    <depth>3</depth>
  </size>
  <segmented>0</segmented>
  <object>
    <name>hand photo</name>
    <difficult>0</difficult>
    <bnd_box>
      <xmin>106.854238467</xmin>
      <xmax>156.585853698</xmax>
      <ymin>201.815181306</ymin>
      <ymax>251.173122787</ymax>
    </bnd_box>
  </object>
</annotation>
