<?xml version="1.0" ?>
<annotation>
  <folder>training_data</folder>
  <filename>VOC2010_1031.jpg</filename>
  <source>
    <database>The oxford hand Database</database>
    <annotation/>
  </source>
  <size>
    <width>500</width>
    <height>375</height>
    <depth>3</depth>
  </size>
  <segmented>0</segmented>
  <object>
    <name>hand photo</name>
    <difficult>0</difficult>
    <bnd_box>
      <xmin>19.268622787</xmin>
      <xmax>70.7682435725</xmax>
      <ymin>241.095153579</ymin>
      <ymax>283.565665135</ymax>
    </bnd_box>
  </object>
  <object>
    <name>hand photo</name>
    <difficult>0</difficult>
    <bnd_box>
      <xmin>143.260346686</xmin>
      <xmax>207.928593406</xmax>
      <ymin>161.164399547</ymin>
      <ymax>203.578290511</ymax>
    </bnd_box>
  </object>
  <object>
    <name>hand photo</name>
    <difficult>0</difficult>
    <bnd_box>
      <xmin>240.248965486</xmin>
      <xmax>268.72799304</xmax>
      <ymin>176.690569972</ymin>
      <ymax>210.180775058</ymax>
    </bnd_box>
  </object>
</annotation>
