<?xml version="1.0" ?>
<annotation>
  <folder>test_data</folder>
  <filename>VOC2007_128.jpg</filename>
  <source>
    <database>The oxford hand Database</database>
    <annotation/>
  </source>
  <size>
    <width>500</width>
    <height>375</height>
    <depth>3</depth>
  </size>
  <segmented>0</segmented>
  <object>
    <name>hand photo</name>
    <difficult>0</difficult>
    <bnd_box>
      <xmin>19.1800350522</xmin>
      <xmax>75.771577851</xmax>
      <ymin>254.233725125</ymin>
      <ymax>292.517908862</ymax>
    </bnd_box>
  </object>
</annotation>
